<?xml version="1.0" encoding="utf-8" ?>
<RotatorManifest>
  <Description>
    This displays the content images (each 566px wide) with the titles floating on the right with a background image.
    Each title is 41px high, so the content image should be 205 px tall if there are five items, and otherwise adjusted accordingly.
    Not intended to be used with the next, previous, or pause buttons, or the position thumbnail.
  </Description>
  <Preview>Preview.png</Preview>
  <Stylesheet>Style.css</Stylesheet>
  <Settings>
    <Setting>
      <Name>ShowContentHeader</Name>
      <Value>False</Value>
    </Setting>
    <Setting>
      <Name>ShowContentHeaderLink</Name>
      <Value>False</Value>
    </Setting>
    <Setting>
      <Name>ShowReadMoreLink</Name>
      <Value>False</Value>
    </Setting>
    <Setting>
      <Name>ControlsShowNextButton</Name>
      <Value>False</Value>
    </Setting>
    <Setting>
      <Name>ControlsShowPrevButton</Name>
      <Value>False</Value>
    </Setting>
    <Setting>
      <Name>ControlsShowPauseButton</Name>
      <Value>False</Value>
    </Setting>
    <Setting>
      <Name>UseAnimations</Name>
      <Value>True</Value>
    </Setting>
    <Setting>
      <Name>AnimationPauseOnMouseOver</Name>
      <Value>True</Value>
    </Setting>
    <Setting>
      <Name>RotatorWidth</Name>
      <Value/>
    </Setting>
    <Setting>
      <Name>RotatorHeight</Name>
      <Value/>
    </Setting>
    <Setting>
      <Name>ThumbnailWidth</Name>
      <Value/>
    </Setting>
    <Setting>
      <Name>ThumbnailHeight</Name>
      <Value/>
    </Setting>
    <Setting>
      <Name>ControlsTitleDisplayMode</Name>
      <Value>RotateContent</Value>
    </Setting>
    <Setting>
      <Name>ContentTitleDisplayMode</Name>
      <Value>None</Value>
    </Setting>
    <Setting>
      <Name>ContentDisplayMode</Name>
      <Value>None</Value>
    </Setting>
    <Setting>
      <Name>ThumbnailDisplayMode</Name>
      <Value>Content</Value>
    </Setting>
    <Setting>
      <Name>PositionThumbnailDisplayMode</Name>
      <Value>None</Value>
    </Setting>
  </Settings>
</RotatorManifest>